LaangYB/__init__.py
LaangYB/admin.py
LaangYB/alive.py
LaangYB/button.py
LaangYB/carbon.py
LaangYB/font.py
LaangYB/gcast.py
LaangYB/get_id.py
LaangYB/globals.py
LaangYB/help.py
LaangYB/info.py
LaangYB/langs.py
LaangYB/log.py
LaangYB/openai.py
LaangYB/paste.py
LaangYB/ping.py
LaangYB/pmpermit.py
LaangYB/purge.py
LaangYB/stickers.py
LaangYB/telegraph.py
LaangYB/tiktok.py
LaangYB/tools.py
LaangYB/translate.py
LaangYB/update.py
LaangYB/vars.py
LaangYB/vcplugin.py
LaangYB/vctools.py
LaangYB/xxx.py
assets/__init__.py
assistant/__init__.py
assistant/callback.py
assistant/inline.py
assistant/start.py
pyLnnggg_0.1.0-0.1.0.dist-info/LICENSE
pyLnnggg_0.1.0-0.1.0.dist-info/METADATA
pyLnnggg_0.1.0-0.1.0.dist-info/WHEEL
pyLnnggg_0.1.0-0.1.0.dist-info/top_level.txt
pyLnnggg_0.1.0-0.1.0.dist-info/RECORD
