Metadata-Version: 2.1
Name: pyLnnggg-0.1.0
Version: 0.1.0
Summary: bot ini dibuat untuk to the point aja 
Home-page: https://github.com/LaangYB/LaangUbot
Author: LaangYB
Author-email: sedekgaming123@gmail.com
License: UNKNOWN
Platform: UNKNOWN
Classifier: Programming Language :: Python :: 3
Classifier: License :: OSI Approved :: MIT License
Classifier: Operating System :: OS Independent
Requires-Python: >=3.6
License-File: LICENSE
Requires-Dist: numpy
Requires-Dist: requests
